flomutils/__init__.py
flomutils/__main__.py
flomutils/cli.py
flomutils/noise.py
flomutils/plot.py
flomutils-0.1.0.dist-info/entry_points.txt
flomutils-0.1.0.dist-info/WHEEL
flomutils-0.1.0.dist-info/METADATA
flomutils-0.1.0.dist-info/RECORD
